llm_zhipu.py
llm_zhipu-0.4.1.dist-info/METADATA
llm_zhipu-0.4.1.dist-info/WHEEL
llm_zhipu-0.4.1.dist-info/entry_points.txt
llm_zhipu-0.4.1.dist-info/licenses/LICENSE
llm_zhipu-0.4.1.dist-info/RECORD
