Metadata-Version: 2.3
Name: llm-zhipu
Version: 0.4.1
Summary: ChatGLM
Project-URL: Homepage, https://github.com/noahlias/llm-zhipu
Project-URL: Changelog, https://github.com/noahlias/llm-zhipu/releases
Project-URL: Issues, https://github.com/noahlias/llm-zhipu/issues
Project-URL: CI, https://github.com/noahlias/llm-zhipu/actions
Author: noahlias
License: Apache-2.0
License-File: LICENSE
Classifier: License :: OSI Approved :: Apache Software License
Requires-Dist: llm
Requires-Dist: zhipuai
Provides-Extra: test
Requires-Dist: pytest; extra == 'test'
